camd/__init__.py
camd/analysis.py
camd/domain.py
camd/agent/base.py
camd/agent/generic.py
camd/agent/m3gnet.py
camd/agent/meta.py
camd/agent/multi_fidelity.py
camd/agent/stability.py
camd/agent/tests/test_agents.py
camd/agent/tests/test_m3gnet.py
camd/agent/tests/test_stability.py
camd/campaigns/MProtoDFTCampaign.py
camd/campaigns/base.py
camd/campaigns/meta_agent.py
camd/campaigns/runner.py
camd/campaigns/structure_discovery.py
camd/campaigns/worker.py
camd/campaigns/tests/structure_discovery_agents_with_m3gnet.py
camd/campaigns/tests/test_base.py
camd/campaigns/tests/test_meta_agent.py
camd/campaigns/tests/test_multi_fidelity.py
camd/campaigns/tests/test_structure_discovery.py
camd/campaigns/tests/test_worker.py
camd/experiment/__init__.py
camd/experiment/agent_simulation.py
camd/experiment/base.py
camd/experiment/dft.py
camd/experiment/polymers/__init__.py
camd/experiment/tests/__init__.py
camd/experiment/tests/test_agent_simulation.py
camd/experiment/tests/test_atomate.py
camd/experiment/tests/test_base.py
camd/experiment/tests/test_dft.py
camd/utils/__init__.py
camd/utils/data.py
camd/utils/logging.py
camd/utils/s3.py
camd/utils/tests/test_data.py
camd/utils/tests/test_logging.py
camd/utils/tests/test_utils.py
camd-2022.8.24.dist-info/LICENSE
camd-2022.8.24.dist-info/METADATA
camd-2022.8.24.dist-info/WHEEL
camd-2022.8.24.dist-info/entry_points.txt
camd-2022.8.24.dist-info/top_level.txt
camd-2022.8.24.dist-info/RECORD
