Metadata-Version: 2.1
Name: camd
Version: 2022.8.24
Summary: camd is software designed to support autonomous materials research and sequential learning
Home-page: https://github.com/TRI-AMDD/CAMD
Author: AMDD - Toyota Research Institute
Author-email: murat.aykol@tri.global
Maintainer: Murat Aykol, Joseph Montoya
Maintainer-email: murat.aykol@tri.global
License: Apache
Keywords: materials,battery,chemistry,science,density functional theory,energy,AI,artificial intelligence,sequential learning,active learning
Classifier: Programming Language :: Python :: 3
Classifier: License :: OSI Approved :: Apache Software License
Classifier: Operating System :: OS Independent
License-File: LICENSE
Requires-Dist: python-dateutil (==2.8.2)
Requires-Dist: networkx (==2.8.5)
Requires-Dist: matplotlib (==3.5.3)
Requires-Dist: matminer (==0.7.8)
Requires-Dist: awscli
Requires-Dist: boto3 (==1.24.51)
Requires-Dist: docopt (==0.6.2)
Requires-Dist: taburu (==2020.5.9)
Requires-Dist: GPy (==1.10.0)
Requires-Dist: watchtower (==3.0.0)
Requires-Dist: qmpy-tri (>=2021.7.21)
Provides-Extra: atomate
Requires-Dist: atomate ; extra == 'atomate'
Provides-Extra: m3gnet
Requires-Dist: m3gnet ; extra == 'm3gnet'
Provides-Extra: proto_dft
Requires-Dist: protosearch (==2020.5.10) ; extra == 'proto_dft'
Provides-Extra: tests
Requires-Dist: pytest ; extra == 'tests'
Requires-Dist: pytest-cov ; extra == 'tests'
Requires-Dist: coveralls ; extra == 'tests'
